{
  "solution_id": "S238",
  "problem_id": "Theme_3",
  "team_name": "ProcureShield AI - Explainable Tender Eligibility Evaluation Platform for Government Procurement",
  "summary": "Design a technical platform that, given a tender document and a set of bidder submissions, can understand the tender, understand each bidder, evaluate eligibility, and produce explainable evaluation reports for government procurement officers.",
  "approach_type": "hybrid",
  "tech_stack": [
    "Large Language Model API",
    "Tesseract OCR",
    "Google Document AI",
    "PostgreSQL",
    "Next.js",
    "PDF.js",
    "FastAPI (Python)"
  ],
  "key_steps": [
    "Tender Intelligence Engine",
    "Bidder Document Parser and Evaluator",
    "Human-in-the-Loop Verification and Audit"
  ],
  "optimization_claims": [
    "No bidder is silently disqualified; every ambiguous case is flagged for human review.",
    "All AI decisions run on submitted documents no raw PII is sent to external services."
  ],
  "constraints_addressed": [
    "Evaluating bid submissions manually is slow, inconsistent, and prone to human error",
    "There is no audit trail",
    "Legally risky to silently disqualify ambiguous bidders"
  ],
  "missing_components": [],
  "strengths": [],
  "weaknesses": []
}