{
  "solution_id": "S676",
  "problem_id": "Theme_3",
  "team_name": "Quorix – AI Decision Intelligence for Transparent and Defensible Procurement",
  "summary": "AI-Based Tender Evaluation and Eligibility Analysis for Government Procurement by CRPF",
  "approach_type": "hybrid",
  "tech_stack": [
    "Natural Language Processing (NLP)",
    "Optical Character Recognition (OCR)"
  ],
  "key_steps": [
    "Semantic extraction of eligibility criteria",
    "Processing heterogeneous bidder documents",
    "Structured evaluation engine",
    "Scenario-aware decision layer",
    "Fraud detection",
    "Price anomaly analysis",
    "Bias identification"
  ],
  "optimization_claims": [
    "What-if simulation of policy and threshold changes",
    "Uncovering hidden patterns",
    "Shift from static evaluation to simulation-driven decision support"
  ],
  "constraints_addressed": [
    "Transparency",
    "Auditability",
    "Defensibility",
    "Fairness",
    "Risk awareness"
  ],
  "missing_components": [],
  "strengths": [],
  "weaknesses": []
}