{"solution_id":"S353","problem_id":"CDP-VerifiedActionPlans","team_name":"CDP (Court Directive Processor): From Court Judgments to Verified Action Plans","summary":"AI system for generating structured action plans from court judgments PDFs, ensuring human-verified data is presented in a dashboard.","approach_type":"hybrid","tech_stack":["NLP","PDF processing"],"key_steps":["Key information extraction","Legal content analysis","Action plan generation","Human-in-the-loop verification","Dashboard creation"],"optimization_claims":["Reducing manual effort in judgment interpretation","Minimizing missed directives and deadlines","Improving compliance response time","Enabling structured and auditable workflows"],"constraints_addressed":["Handling complex, inconsistent legal PDFs","Outputs must be explainable and verifiable","Focus on decision support, not full automation"],"missing_components":[],"strengths":[],"weaknesses":[]}