{
  "solution_id": "S049",
  "problem_id": "Theme_2",
  "team_name": "SetuSync AI: Two-Way Interoperability Layer for SWS and Department Systems",
  "summary": "Design a layer for two-way interoperability between Karnataka's Single Window System and legacy department systems using UBID as the common join key.",
  "approach_type": "hybrid",
  "tech_stack": [
    "SetuSync AI"
  ],
  "key_steps": [
    "Translation of requests",
    "Handling retries, duplicates, conflicts, and failures",
    "Logging of every propagation",
    "Configurable policies for conflicting updates",
    "Schema mappings",
    "Audit trails"
  ],
  "optimization_claims": [
    "Idempotent propagations",
    "Traceability",
    "Reliability",
    "Reversibility"
  ],
  "constraints_addressed": [
    "Systems cannot be modified",
    "Differing schemas across departments",
    "Service requests may originate from either side"
  ],
  "missing_components": [],
  "strengths": [],
  "weaknesses": []
}