{
  "solution_id": "S221",
  "problem_id": "Theme_2",
  "team_name": "Jfcbjnbgc",
  "summary": "Design a layer for two-way interoperability between Karnataka's Single Window System and legacy department systems using Unique Business Identifier (UBID) as the common join key.",
  "approach_type": "hybrid",
  "tech_stack": [
    "API"
  ],
  "key_steps": [
    "Identify the required data for propagation",
    "Define APIs for bi-directional communication",
    "Implement the UBID-based mapping layer",
    "Test and deploy the solution"
  ],
  "optimization_claims": [],
  "constraints_addressed": [
    "Data inconsistency across systems",
    "Manual data entry",
    "Lack of real-time updates"
  ],
  "missing_components": [
    "Detailed error handling mechanism",
    "Monitoring and logging tools"
  ],
  "strengths": [],
  "weaknesses": []
}